{"crate":"typst_utils","nodes":[{"path":"alloc::alloc::Global","name":"Global","kind":"struct","visibility":"pub"},{"path":"alloc::fmt","name":"fmt","kind":"mod","visibility":"pub"},{"path":"alloc::sync::Arc","name":"Arc","kind":"struct","visibility":"pub"},{"path":"alloc::vec::Vec","name":"Vec","kind":"struct","visibility":"pub"},{"path":"core::alloc::layout::Layout","name":"Layout","kind":"struct","visibility":"pub"},{"path":"core::borrow::Borrow","name":"Borrow","kind":"trait","visibility":"pub"},{"path":"core::cmp::Ordering","name":"Ordering","kind":"enum","visibility":"pub"},{"path":"core::fmt::Debug","name":"Debug","kind":"trait","visibility":"pub"},{"path":"core::fmt::Display","name":"Display","kind":"trait","visibility":"pub"},{"path":"core::fmt::Error","name":"Error","kind":"struct","visibility":"pub"},{"path":"core::fmt::Formatter","name":"Formatter","kind":"struct","visibility":"pub"},{"path":"core::fmt::Write","name":"Write","kind":"trait","visibility":"pub"},{"path":"core::fmt::macros::Debug","name":"Debug","kind":"macro","visibility":"pub"},{"path":"core::hash::Hash","name":"Hash","kind":"trait","visibility":"pub"},{"path":"core::hash::Hasher","name":"Hasher","kind":"trait","visibility":"pub"},{"path":"core::hash::macros::Hash","name":"Hash","kind":"macro","visibility":"pub"},{"path":"core::iter::adapters::chain::Chain","name":"Chain","kind":"struct","visibility":"pub"},{"path":"core::iter::adapters::flatten::Flatten","name":"Flatten","kind":"struct","visibility":"pub"},{"path":"core::iter::adapters::rev::Rev","name":"Rev","kind":"struct","visibility":"pub"},{"path":"core::iter::traits::accum::Sum","name":"Sum","kind":"trait","visibility":"pub"},{"path":"core::iter::traits::iterator::Iterator","name":"Iterator","kind":"trait","visibility":"pub"},{"path":"core::marker::Sized","name":"Sized","kind":"trait","visibility":"pub"},{"path":"core::mem","name":"mem","kind":"mod","visibility":"pub"},{"path":"core::num::nonzero::NonZero","name":"NonZero","kind":"struct","visibility":"pub"},{"path":"core::num::nonzero::NonZeroU32","name":"NonZeroU32","kind":"type","visibility":"pub"},{"path":"core::num::nonzero::NonZeroU64","name":"NonZeroU64","kind":"type","visibility":"pub"},{"path":"core::num::nonzero::NonZeroUsize","name":"NonZeroUsize","kind":"type","visibility":"pub"},{"path":"core::ops::arith::Add","name":"Add","kind":"trait","visibility":"pub"},{"path":"core::ops::arith::Div","name":"Div","kind":"trait","visibility":"pub"},{"path":"core::ops::arith::Mul","name":"Mul","kind":"trait","visibility":"pub"},{"path":"core::ops::arith::Neg","name":"Neg","kind":"trait","visibility":"pub"},{"path":"core::ops::arith::Rem","name":"Rem","kind":"trait","visibility":"pub"},{"path":"core::ops::arith::Sub","name":"Sub","kind":"trait","visibility":"pub"},{"path":"core::ops::deref::Deref","name":"Deref","kind":"trait","visibility":"pub"},{"path":"core::ops::deref::DerefMut","name":"DerefMut","kind":"trait","visibility":"pub"},{"path":"core::ops::function::FnOnce","name":"FnOnce","kind":"trait","visibility":"pub"},{"path":"core::option::Option","name":"Option","kind":"enum","visibility":"pub"},{"path":"core::ptr::non_null::NonNull","name":"NonNull","kind":"struct","visibility":"pub"},{"path":"core::result::Result","name":"Result","kind":"enum","visibility":"pub"},{"path":"core::sync::atomic::Ordering","name":"Ordering","kind":"enum","visibility":"pub"},{"path":"core::time::Duration","name":"Duration","kind":"struct","visibility":"pub"},{"path":"once_cell","name":"once_cell","kind":"crate","visibility":"pub"},{"path":"once_cell::sync::OnceCell","name":"OnceCell","kind":"struct","visibility":"pub"},{"path":"portable_atomic::AtomicU128","name":"AtomicU128","kind":"struct","visibility":"pub"},{"path":"rustc_hash::FxBuildHasher","name":"FxBuildHasher","kind":"struct","visibility":"pub"},{"path":"rustc_hash::FxHashMap","name":"FxHashMap","kind":"type","visibility":"pub"},{"path":"siphasher::sip128::Hasher128","name":"Hasher128","kind":"trait","visibility":"pub"},{"path":"siphasher::sip128::SipHasher13","name":"SipHasher13","kind":"struct","visibility":"pub"},{"path":"std::collections::hash::map::HashMap","name":"HashMap","kind":"struct","visibility":"pub"},{"path":"std::sync::lazy_lock::LazyLock","name":"LazyLock","kind":"struct","visibility":"pub"},{"path":"std::sync::poison::rwlock::RwLock","name":"RwLock","kind":"struct","visibility":"pub"},{"path":"thin_vec::ThinVec","name":"ThinVec","kind":"struct","visibility":"pub"},{"path":"typst_utils","name":"typst_utils","kind":"crate","visibility":"pub"},{"path":"typst_utils::ArcExt","name":"ArcExt","kind":"trait","visibility":"pub"},{"path":"typst_utils::Get","name":"Get","kind":"trait","visibility":"pub"},{"path":"typst_utils::GroupByKey","name":"GroupByKey","kind":"struct","visibility":"pub"},{"path":"typst_utils::GroupByKey::Item","name":"Item","kind":"type","visibility":"pub(crate)"},{"path":"typst_utils::GroupByKey::next","name":"next","kind":"fn","visibility":"pub(crate)"},{"path":"typst_utils::MaybeReverseIter","name":"MaybeReverseIter","kind":"trait","visibility":"pub"},{"path":"typst_utils::NonZeroExt","name":"NonZeroExt","kind":"trait","visibility":"pub"},{"path":"typst_utils::Numeric","name":"Numeric","kind":"trait","visibility":"pub"},{"path":"typst_utils::OptionExt","name":"OptionExt","kind":"trait","visibility":"pub"},{"path":"typst_utils::SliceExt","name":"SliceExt","kind":"trait","visibility":"pub"},{"path":"typst_utils::Static","name":"Static","kind":"struct","visibility":"pub"},{"path":"typst_utils::Static::Target","name":"Target","kind":"type","visibility":"pub(crate)"},{"path":"typst_utils::Static::clone","name":"clone","kind":"fn","visibility":"pub(crate)"},{"path":"typst_utils::Static::deref","name":"deref","kind":"fn","visibility":"pub(crate)"},{"path":"typst_utils::Static::eq","name":"eq","kind":"fn","visibility":"pub(crate)"},{"path":"typst_utils::Static::fmt","name":"fmt","kind":"fn","visibility":"pub"},{"path":"typst_utils::Static::hash","name":"hash","kind":"fn","visibility":"pub(crate)"},{"path":"typst_utils::bitset","name":"bitset","kind":"mod","visibility":"pub(crate)"},{"path":"typst_utils::bitset::BitSet","name":"BitSet","kind":"struct","visibility":"pub"},{"path":"typst_utils::bitset::BitSet::clone","name":"clone","kind":"fn","visibility":"pub"},{"path":"typst_utils::bitset::BitSet::contains","name":"contains","kind":"fn","visibility":"pub"},{"path":"typst_utils::bitset::BitSet::default","name":"default","kind":"fn","visibility":"priv"},{"path":"typst_utils::bitset::BitSet::eq","name":"eq","kind":"fn","visibility":"pub"},{"path":"typst_utils::bitset::BitSet::fmt","name":"fmt","kind":"fn","visibility":"priv"},{"path":"typst_utils::bitset::BitSet::hash","name":"hash","kind":"fn","visibility":"pub"},{"path":"typst_utils::bitset::BitSet::insert","name":"insert","kind":"fn","visibility":"pub"},{"path":"typst_utils::bitset::BitSet::new","name":"new","kind":"fn","visibility":"pub"},{"path":"typst_utils::bitset::SmallBitSet","name":"SmallBitSet","kind":"struct","visibility":"pub"},{"path":"typst_utils::bitset::SmallBitSet::clone","name":"clone","kind":"fn","visibility":"pub"},{"path":"typst_utils::bitset::SmallBitSet::contains","name":"contains","kind":"fn","visibility":"pub"},{"path":"typst_utils::bitset::SmallBitSet::default","name":"default","kind":"fn","visibility":"priv"},{"path":"typst_utils::bitset::SmallBitSet::eq","name":"eq","kind":"fn","visibility":"pub"},{"path":"typst_utils::bitset::SmallBitSet::fmt","name":"fmt","kind":"fn","visibility":"priv"},{"path":"typst_utils::bitset::SmallBitSet::hash","name":"hash","kind":"fn","visibility":"pub"},{"path":"typst_utils::bitset::SmallBitSet::insert","name":"insert","kind":"fn","visibility":"pub"},{"path":"typst_utils::bitset::SmallBitSet::new","name":"new","kind":"fn","visibility":"pub"},{"path":"typst_utils::debug","name":"debug","kind":"fn","visibility":"pub"},{"path":"typst_utils::default_math_class","name":"default_math_class","kind":"fn","visibility":"pub"},{"path":"typst_utils::defer","name":"defer","kind":"fn","visibility":"pub"},{"path":"typst_utils::deferred","name":"deferred","kind":"mod","visibility":"pub(crate)"},{"path":"typst_utils::deferred::Deferred","name":"Deferred","kind":"struct","visibility":"pub"},{"path":"typst_utils::deferred::Deferred::clone","name":"clone","kind":"fn","visibility":"priv"},{"path":"typst_utils::deferred::Deferred::new","name":"new","kind":"fn","visibility":"pub"},{"path":"typst_utils::deferred::Deferred::wait","name":"wait","kind":"fn","visibility":"pub"},{"path":"typst_utils::display","name":"display","kind":"fn","visibility":"pub"},{"path":"typst_utils::duration","name":"duration","kind":"mod","visibility":"pub(crate)"},{"path":"typst_utils::duration::DurationDisplay","name":"DurationDisplay","kind":"struct","visibility":"priv"},{"path":"typst_utils::duration::DurationDisplay::fmt","name":"fmt","kind":"fn","visibility":"priv"},{"path":"typst_utils::duration::format_duration","name":"format_duration","kind":"fn","visibility":"pub"},{"path":"typst_utils::fat","name":"fat","kind":"mod","visibility":"pub"},{"path":"typst_utils::fat::FatPointer","name":"FatPointer","kind":"struct","visibility":"priv"},{"path":"typst_utils::fat::from_raw_parts","name":"from_raw_parts","kind":"unsafe fn","visibility":"pub"},{"path":"typst_utils::fat::from_raw_parts_mut","name":"from_raw_parts_mut","kind":"unsafe fn","visibility":"pub"},{"path":"typst_utils::fat::vtable","name":"vtable","kind":"unsafe fn","visibility":"pub"},{"path":"typst_utils::hash","name":"hash","kind":"mod","visibility":"pub(crate)"},{"path":"typst_utils::hash::HashLock","name":"HashLock","kind":"struct","visibility":"pub"},{"path":"typst_utils::hash::HashLock::clone","name":"clone","kind":"fn","visibility":"priv"},{"path":"typst_utils::hash::HashLock::default","name":"default","kind":"fn","visibility":"priv"},{"path":"typst_utils::hash::HashLock::get","name":"get","kind":"fn","visibility":"priv"},{"path":"typst_utils::hash::HashLock::get_or_insert_with","name":"get_or_insert_with","kind":"fn","visibility":"pub"},{"path":"typst_utils::hash::HashLock::new","name":"new","kind":"const fn","visibility":"pub"},{"path":"typst_utils::hash::HashLock::reset","name":"reset","kind":"fn","visibility":"pub"},{"path":"typst_utils::hash::LazyHash","name":"LazyHash","kind":"struct","visibility":"pub"},{"path":"typst_utils::hash::LazyHash::Target","name":"Target","kind":"type","visibility":"priv"},{"path":"typst_utils::hash::LazyHash::clone","name":"clone","kind":"fn","visibility":"pub"},{"path":"typst_utils::hash::LazyHash::default","name":"default","kind":"fn","visibility":"priv"},{"path":"typst_utils::hash::LazyHash::deref","name":"deref","kind":"fn","visibility":"priv"},{"path":"typst_utils::hash::LazyHash::deref_mut","name":"deref_mut","kind":"fn","visibility":"priv"},{"path":"typst_utils::hash::LazyHash::eq","name":"eq","kind":"fn","visibility":"priv"},{"path":"typst_utils::hash::LazyHash::fmt","name":"fmt","kind":"fn","visibility":"priv"},{"path":"typst_utils::hash::LazyHash::from","name":"from","kind":"fn","visibility":"priv"},{"path":"typst_utils::hash::LazyHash::hash","name":"hash","kind":"fn","visibility":"priv"},{"path":"typst_utils::hash::LazyHash::into_inner","name":"into_inner","kind":"fn","visibility":"pub"},{"path":"typst_utils::hash::LazyHash::load_or_compute_hash","name":"load_or_compute_hash","kind":"fn","visibility":"priv"},{"path":"typst_utils::hash::LazyHash::new","name":"new","kind":"fn","visibility":"pub"},{"path":"typst_utils::hash::ManuallyHash","name":"ManuallyHash","kind":"struct","visibility":"pub"},{"path":"typst_utils::hash::ManuallyHash::Target","name":"Target","kind":"type","visibility":"priv"},{"path":"typst_utils::hash::ManuallyHash::clone","name":"clone","kind":"fn","visibility":"pub"},{"path":"typst_utils::hash::ManuallyHash::deref","name":"deref","kind":"fn","visibility":"priv"},{"path":"typst_utils::hash::ManuallyHash::eq","name":"eq","kind":"fn","visibility":"priv"},{"path":"typst_utils::hash::ManuallyHash::fmt","name":"fmt","kind":"fn","visibility":"priv"},{"path":"typst_utils::hash::ManuallyHash::hash","name":"hash","kind":"fn","visibility":"priv"},{"path":"typst_utils::hash::ManuallyHash::into_inner","name":"into_inner","kind":"fn","visibility":"pub"},{"path":"typst_utils::hash::ManuallyHash::new","name":"new","kind":"fn","visibility":"pub"},{"path":"typst_utils::hash::hash128","name":"hash128","kind":"fn","visibility":"pub"},{"path":"typst_utils::listset","name":"listset","kind":"mod","visibility":"pub(crate)"},{"path":"typst_utils::listset::ListSet","name":"ListSet","kind":"struct","visibility":"pub"},{"path":"typst_utils::listset::ListSet::contains","name":"contains","kind":"fn","visibility":"pub"},{"path":"typst_utils::listset::ListSet::is_empty","name":"is_empty","kind":"fn","visibility":"pub"},{"path":"typst_utils::listset::ListSet::new","name":"new","kind":"fn","visibility":"pub"},{"path":"typst_utils::macros","name":"macros","kind":"mod","visibility":"pub(crate)"},{"path":"typst_utils::macros::assign_impl","name":"assign_impl","kind":"macro","visibility":"pub"},{"path":"typst_utils::macros::display","name":"display","kind":"macro","visibility":"pub"},{"path":"typst_utils::macros::singleton","name":"singleton","kind":"macro","visibility":"pub"},{"path":"typst_utils::macros::sub_impl","name":"sub_impl","kind":"macro","visibility":"pub"},{"path":"typst_utils::option::Option::map_or_default","name":"map_or_default","kind":"fn","visibility":"pub(crate)"},{"path":"typst_utils::option_eq","name":"option_eq","kind":"fn","visibility":"pub"},{"path":"typst_utils::pico","name":"pico","kind":"mod","visibility":"pub(crate)"},{"path":"typst_utils::pico::Interner","name":"Interner","kind":"struct","visibility":"priv"},{"path":"typst_utils::pico::PicoStr","name":"PicoStr","kind":"struct","visibility":"pub"},{"path":"typst_utils::pico::PicoStr::clone","name":"clone","kind":"fn","visibility":"pub"},{"path":"typst_utils::pico::PicoStr::constant","name":"constant","kind":"const fn","visibility":"pub"},{"path":"typst_utils::pico::PicoStr::eq","name":"eq","kind":"fn","visibility":"pub"},{"path":"typst_utils::pico::PicoStr::fmt","name":"fmt","kind":"fn","visibility":"priv"},{"path":"typst_utils::pico::PicoStr::get","name":"get","kind":"fn","visibility":"pub"},{"path":"typst_utils::pico::PicoStr::hash","name":"hash","kind":"fn","visibility":"pub"},{"path":"typst_utils::pico::PicoStr::intern","name":"intern","kind":"fn","visibility":"pub"},{"path":"typst_utils::pico::PicoStr::resolve","name":"resolve","kind":"fn","visibility":"pub"},{"path":"typst_utils::pico::PicoStr::try_constant","name":"try_constant","kind":"const fn","visibility":"pub"},{"path":"typst_utils::pico::ResolvedPicoStr","name":"ResolvedPicoStr","kind":"struct","visibility":"pub"},{"path":"typst_utils::pico::ResolvedPicoStr::Target","name":"Target","kind":"type","visibility":"priv"},{"path":"typst_utils::pico::ResolvedPicoStr::as_ref","name":"as_ref","kind":"fn","visibility":"priv"},{"path":"typst_utils::pico::ResolvedPicoStr::as_str","name":"as_str","kind":"fn","visibility":"pub"},{"path":"typst_utils::pico::ResolvedPicoStr::borrow","name":"borrow","kind":"fn","visibility":"priv"},{"path":"typst_utils::pico::ResolvedPicoStr::clone","name":"clone","kind":"fn","visibility":"pub"},{"path":"typst_utils::pico::ResolvedPicoStr::cmp","name":"cmp","kind":"fn","visibility":"priv"},{"path":"typst_utils::pico::ResolvedPicoStr::deref","name":"deref","kind":"fn","visibility":"priv"},{"path":"typst_utils::pico::ResolvedPicoStr::eq","name":"eq","kind":"fn","visibility":"priv"},{"path":"typst_utils::pico::ResolvedPicoStr::fmt","name":"fmt","kind":"fn","visibility":"priv"},{"path":"typst_utils::pico::ResolvedPicoStr::fmt","name":"fmt","kind":"fn","visibility":"priv"},{"path":"typst_utils::pico::ResolvedPicoStr::hash","name":"hash","kind":"fn","visibility":"priv"},{"path":"typst_utils::pico::ResolvedPicoStr::partial_cmp","name":"partial_cmp","kind":"fn","visibility":"priv"},{"path":"typst_utils::pico::ResolvedPicoStrInner","name":"ResolvedPicoStrInner","kind":"enum","visibility":"priv"},{"path":"typst_utils::pico::ResolvedPicoStrInner::clone","name":"clone","kind":"fn","visibility":"pub"},{"path":"typst_utils::pico::bitcode","name":"bitcode","kind":"mod","visibility":"priv"},{"path":"typst_utils::pico::bitcode::EncodingError","name":"EncodingError","kind":"enum","visibility":"pub"},{"path":"typst_utils::pico::bitcode::EncodingError::message","name":"message","kind":"const fn","visibility":"pub"},{"path":"typst_utils::pico::bitcode::decode","name":"decode","kind":"const fn","visibility":"pub"},{"path":"typst_utils::pico::bitcode::encode","name":"encode","kind":"const fn","visibility":"pub"},{"path":"typst_utils::pico::exceptions","name":"exceptions","kind":"mod","visibility":"priv"},{"path":"typst_utils::pico::exceptions::get","name":"get","kind":"const fn","visibility":"pub"},{"path":"typst_utils::pico::exceptions::min","name":"min","kind":"const fn","visibility":"priv"},{"path":"typst_utils::pico::exceptions::strcmp","name":"strcmp","kind":"const fn","visibility":"priv"},{"path":"typst_utils::pico::failed_to_compile_time_intern","name":"failed_to_compile_time_intern","kind":"const fn","visibility":"priv"},{"path":"typst_utils::protected","name":"protected","kind":"mod","visibility":"pub(crate)"},{"path":"typst_utils::protected::Protected","name":"Protected","kind":"struct","visibility":"pub"},{"path":"typst_utils::protected::Protected::access","name":"access","kind":"fn","visibility":"pub"},{"path":"typst_utils::protected::Protected::clone","name":"clone","kind":"fn","visibility":"pub"},{"path":"typst_utils::protected::Protected::fmt","name":"fmt","kind":"fn","visibility":"pub"},{"path":"typst_utils::protected::Protected::from_raw","name":"from_raw","kind":"fn","visibility":"pub"},{"path":"typst_utils::protected::Protected::into_raw","name":"into_raw","kind":"fn","visibility":"pub"},{"path":"typst_utils::protected::Protected::new","name":"new","kind":"fn","visibility":"pub"},{"path":"typst_utils::round","name":"round","kind":"mod","visibility":"pub(crate)"},{"path":"typst_utils::round::round_int_with_precision","name":"round_int_with_precision","kind":"fn","visibility":"pub"},{"path":"typst_utils::round::round_with_precision","name":"round_with_precision","kind":"fn","visibility":"pub"},{"path":"typst_utils::scalar","name":"scalar","kind":"mod","visibility":"pub(crate)"},{"path":"typst_utils::scalar::Scalar","name":"Scalar","kind":"struct","visibility":"pub"},{"path":"typst_utils::scalar::Scalar::Output","name":"Output","kind":"type","visibility":"priv"},{"path":"typst_utils::scalar::Scalar::Output","name":"Output","kind":"type","visibility":"priv"},{"path":"typst_utils::scalar::Scalar::Output","name":"Output","kind":"type","visibility":"priv"},{"path":"typst_utils::scalar::Scalar::Output","name":"Output","kind":"type","visibility":"priv"},{"path":"typst_utils::scalar::Scalar::Output","name":"Output","kind":"type","visibility":"priv"},{"path":"typst_utils::scalar::Scalar::Output","name":"Output","kind":"type","visibility":"priv"},{"path":"typst_utils::scalar::Scalar::Output","name":"Output","kind":"type","visibility":"priv"},{"path":"typst_utils::scalar::Scalar::Output","name":"Output","kind":"type","visibility":"priv"},{"path":"typst_utils::scalar::Scalar::Output","name":"Output","kind":"type","visibility":"priv"},{"path":"typst_utils::scalar::Scalar::Output","name":"Output","kind":"type","visibility":"priv"},{"path":"typst_utils::scalar::Scalar::Output","name":"Output","kind":"type","visibility":"priv"},{"path":"typst_utils::scalar::Scalar::add","name":"add","kind":"fn","visibility":"priv"},{"path":"typst_utils::scalar::Scalar::add","name":"add","kind":"fn","visibility":"priv"},{"path":"typst_utils::scalar::Scalar::add_assign","name":"add_assign","kind":"fn","visibility":"priv"},{"path":"typst_utils::scalar::Scalar::add_assign","name":"add_assign","kind":"fn","visibility":"priv"},{"path":"typst_utils::scalar::Scalar::clone","name":"clone","kind":"fn","visibility":"pub"},{"path":"typst_utils::scalar::Scalar::cmp","name":"cmp","kind":"fn","visibility":"priv"},{"path":"typst_utils::scalar::Scalar::default","name":"default","kind":"fn","visibility":"pub"},{"path":"typst_utils::scalar::Scalar::div","name":"div","kind":"fn","visibility":"priv"},{"path":"typst_utils::scalar::Scalar::div","name":"div","kind":"fn","visibility":"priv"},{"path":"typst_utils::scalar::Scalar::div_assign","name":"div_assign","kind":"fn","visibility":"priv"},{"path":"typst_utils::scalar::Scalar::div_assign","name":"div_assign","kind":"fn","visibility":"priv"},{"path":"typst_utils::scalar::Scalar::eq","name":"eq","kind":"fn","visibility":"priv"},{"path":"typst_utils::scalar::Scalar::eq","name":"eq","kind":"fn","visibility":"priv"},{"path":"typst_utils::scalar::Scalar::fmt","name":"fmt","kind":"fn","visibility":"priv"},{"path":"typst_utils::scalar::Scalar::from","name":"from","kind":"fn","visibility":"priv"},{"path":"typst_utils::scalar::Scalar::get","name":"get","kind":"const fn","visibility":"pub"},{"path":"typst_utils::scalar::Scalar::hash","name":"hash","kind":"fn","visibility":"priv"},{"path":"typst_utils::scalar::Scalar::is_finite","name":"is_finite","kind":"fn","visibility":"priv"},{"path":"typst_utils::scalar::Scalar::mul","name":"mul","kind":"fn","visibility":"priv"},{"path":"typst_utils::scalar::Scalar::mul","name":"mul","kind":"fn","visibility":"priv"},{"path":"typst_utils::scalar::Scalar::mul_assign","name":"mul_assign","kind":"fn","visibility":"priv"},{"path":"typst_utils::scalar::Scalar::mul_assign","name":"mul_assign","kind":"fn","visibility":"priv"},{"path":"typst_utils::scalar::Scalar::neg","name":"neg","kind":"fn","visibility":"priv"},{"path":"typst_utils::scalar::Scalar::new","name":"new","kind":"const fn","visibility":"pub"},{"path":"typst_utils::scalar::Scalar::partial_cmp","name":"partial_cmp","kind":"fn","visibility":"priv"},{"path":"typst_utils::scalar::Scalar::powi","name":"powi","kind":"fn","visibility":"pub"},{"path":"typst_utils::scalar::Scalar::rem","name":"rem","kind":"fn","visibility":"priv"},{"path":"typst_utils::scalar::Scalar::rem","name":"rem","kind":"fn","visibility":"priv"},{"path":"typst_utils::scalar::Scalar::rem_assign","name":"rem_assign","kind":"fn","visibility":"priv"},{"path":"typst_utils::scalar::Scalar::rem_assign","name":"rem_assign","kind":"fn","visibility":"priv"},{"path":"typst_utils::scalar::Scalar::sqrt","name":"sqrt","kind":"fn","visibility":"pub"},{"path":"typst_utils::scalar::Scalar::sub","name":"sub","kind":"fn","visibility":"priv"},{"path":"typst_utils::scalar::Scalar::sub","name":"sub","kind":"fn","visibility":"priv"},{"path":"typst_utils::scalar::Scalar::sub_assign","name":"sub_assign","kind":"fn","visibility":"priv"},{"path":"typst_utils::scalar::Scalar::sub_assign","name":"sub_assign","kind":"fn","visibility":"priv"},{"path":"typst_utils::scalar::Scalar::sum","name":"sum","kind":"fn","visibility":"priv"},{"path":"typst_utils::scalar::Scalar::sum","name":"sum","kind":"fn","visibility":"priv"},{"path":"typst_utils::scalar::Scalar::zero","name":"zero","kind":"fn","visibility":"priv"},{"path":"typst_utils::sync::Arc::take","name":"take","kind":"fn","visibility":"pub(crate)"},{"path":"typst_utils::version_","name":"version_","kind":"mod","visibility":"pub(crate)"},{"path":"typst_utils::version_::TypstVersion","name":"TypstVersion","kind":"struct","visibility":"pub"},{"path":"typst_utils::version_::TypstVersion::clone","name":"clone","kind":"fn","visibility":"pub"},{"path":"typst_utils::version_::TypstVersion::commit","name":"commit","kind":"fn","visibility":"pub"},{"path":"typst_utils::version_::TypstVersion::fmt","name":"fmt","kind":"fn","visibility":"pub"},{"path":"typst_utils::version_::TypstVersion::major","name":"major","kind":"fn","visibility":"pub"},{"path":"typst_utils::version_::TypstVersion::minor","name":"minor","kind":"fn","visibility":"pub"},{"path":"typst_utils::version_::TypstVersion::patch","name":"patch","kind":"fn","visibility":"pub"},{"path":"typst_utils::version_::TypstVersion::raw","name":"raw","kind":"fn","visibility":"pub"},{"path":"typst_utils::version_::display_commit","name":"display_commit","kind":"fn","visibility":"pub"},{"path":"typst_utils::version_::version","name":"version","kind":"fn","visibility":"pub"},{"path":"unicode_math_class::MathClass","name":"MathClass","kind":"enum","visibility":"pub"}],"edges":[{"from":"alloc::sync::Arc","to":"typst_utils::sync::Arc::take","relation":"owns"},{"from":"core::option::Option","to":"typst_utils::option::Option::map_or_default","relation":"owns"},{"from":"typst_utils","to":"alloc::sync::Arc","relation":"uses"},{"from":"typst_utils","to":"core::fmt::Debug","relation":"uses"},{"from":"typst_utils","to":"core::fmt::Display","relation":"uses"},{"from":"typst_utils","to":"core::fmt::Formatter","relation":"uses"},{"from":"typst_utils","to":"core::fmt::macros::Debug","relation":"uses"},{"from":"typst_utils","to":"core::hash::Hash","relation":"uses"},{"from":"typst_utils","to":"core::hash::macros::Hash","relation":"uses"},{"from":"typst_utils","to":"core::iter::adapters::chain::Chain","relation":"uses"},{"from":"typst_utils","to":"core::iter::adapters::flatten::Flatten","relation":"uses"},{"from":"typst_utils","to":"core::iter::adapters::rev::Rev","relation":"uses"},{"from":"typst_utils","to":"core::num::nonzero::NonZeroU32","relation":"uses"},{"from":"typst_utils","to":"core::num::nonzero::NonZeroUsize","relation":"uses"},{"from":"typst_utils","to":"core::ops::arith::Add","relation":"uses"},{"from":"typst_utils","to":"core::ops::arith::Div","relation":"uses"},{"from":"typst_utils","to":"core::ops::arith::Mul","relation":"uses"},{"from":"typst_utils","to":"core::ops::arith::Neg","relation":"uses"},{"from":"typst_utils","to":"core::ops::arith::Sub","relation":"uses"},{"from":"typst_utils","to":"core::ops::deref::Deref","relation":"uses"},{"from":"typst_utils","to":"core::ops::deref::DerefMut","relation":"uses"},{"from":"typst_utils","to":"once_cell","relation":"uses"},{"from":"typst_utils","to":"typst_utils::ArcExt","relation":"owns"},{"from":"typst_utils","to":"typst_utils::Get","relation":"owns"},{"from":"typst_utils","to":"typst_utils::GroupByKey","relation":"owns"},{"from":"typst_utils","to":"typst_utils::MaybeReverseIter","relation":"owns"},{"from":"typst_utils","to":"typst_utils::NonZeroExt","relation":"owns"},{"from":"typst_utils","to":"typst_utils::Numeric","relation":"owns"},{"from":"typst_utils","to":"typst_utils::OptionExt","relation":"owns"},{"from":"typst_utils","to":"typst_utils::SliceExt","relation":"owns"},{"from":"typst_utils","to":"typst_utils::Static","relation":"owns"},{"from":"typst_utils","to":"typst_utils::bitset","relation":"owns"},{"from":"typst_utils","to":"typst_utils::bitset::BitSet","relation":"uses"},{"from":"typst_utils","to":"typst_utils::bitset::SmallBitSet","relation":"uses"},{"from":"typst_utils","to":"typst_utils::debug","relation":"owns"},{"from":"typst_utils","to":"typst_utils::default_math_class","relation":"owns"},{"from":"typst_utils","to":"typst_utils::defer","relation":"owns"},{"from":"typst_utils","to":"typst_utils::deferred","relation":"owns"},{"from":"typst_utils","to":"typst_utils::deferred::Deferred","relation":"uses"},{"from":"typst_utils","to":"typst_utils::display","relation":"owns"},{"from":"typst_utils","to":"typst_utils::duration","relation":"owns"},{"from":"typst_utils","to":"typst_utils::duration::format_duration","relation":"uses"},{"from":"typst_utils","to":"typst_utils::fat","relation":"owns"},{"from":"typst_utils","to":"typst_utils::hash","relation":"owns"},{"from":"typst_utils","to":"typst_utils::hash::HashLock","relation":"uses"},{"from":"typst_utils","to":"typst_utils::hash::LazyHash","relation":"uses"},{"from":"typst_utils","to":"typst_utils::hash::ManuallyHash","relation":"uses"},{"from":"typst_utils","to":"typst_utils::hash::hash128","relation":"uses"},{"from":"typst_utils","to":"typst_utils::listset","relation":"owns"},{"from":"typst_utils","to":"typst_utils::listset::ListSet","relation":"uses"},{"from":"typst_utils","to":"typst_utils::macros","relation":"owns"},{"from":"typst_utils","to":"typst_utils::macros::assign_impl","relation":"uses"},{"from":"typst_utils","to":"typst_utils::macros::display","relation":"uses"},{"from":"typst_utils","to":"typst_utils::macros::singleton","relation":"uses"},{"from":"typst_utils","to":"typst_utils::macros::sub_impl","relation":"uses"},{"from":"typst_utils","to":"typst_utils::option_eq","relation":"owns"},{"from":"typst_utils","to":"typst_utils::pico","relation":"owns"},{"from":"typst_utils","to":"typst_utils::pico::PicoStr","relation":"uses"},{"from":"typst_utils","to":"typst_utils::pico::ResolvedPicoStr","relation":"uses"},{"from":"typst_utils","to":"typst_utils::protected","relation":"owns"},{"from":"typst_utils","to":"typst_utils::protected::Protected","relation":"uses"},{"from":"typst_utils","to":"typst_utils::round","relation":"owns"},{"from":"typst_utils","to":"typst_utils::round::round_int_with_precision","relation":"uses"},{"from":"typst_utils","to":"typst_utils::round::round_with_precision","relation":"uses"},{"from":"typst_utils","to":"typst_utils::scalar","relation":"owns"},{"from":"typst_utils","to":"typst_utils::scalar::Scalar","relation":"uses"},{"from":"typst_utils","to":"typst_utils::version_","relation":"owns"},{"from":"typst_utils","to":"typst_utils::version_::TypstVersion","relation":"uses"},{"from":"typst_utils","to":"typst_utils::version_::display_commit","relation":"uses"},{"from":"typst_utils","to":"typst_utils::version_::version","relation":"uses"},{"from":"typst_utils","to":"unicode_math_class::MathClass","relation":"uses"},{"from":"typst_utils::GroupByKey","to":"typst_utils::GroupByKey::Item","relation":"owns"},{"from":"typst_utils::GroupByKey","to":"typst_utils::GroupByKey::next","relation":"owns"},{"from":"typst_utils::GroupByKey::next","to":"core::iter::traits::iterator::Iterator","relation":"uses"},{"from":"typst_utils::GroupByKey::next","to":"core::option::Option","relation":"uses"},{"from":"typst_utils::GroupByKey::next","to":"typst_utils::GroupByKey","relation":"uses"},{"from":"typst_utils::Static","to":"typst_utils::Static::Target","relation":"owns"},{"from":"typst_utils::Static","to":"typst_utils::Static::clone","relation":"owns"},{"from":"typst_utils::Static","to":"typst_utils::Static::deref","relation":"owns"},{"from":"typst_utils::Static","to":"typst_utils::Static::eq","relation":"owns"},{"from":"typst_utils::Static","to":"typst_utils::Static::fmt","relation":"owns"},{"from":"typst_utils::Static","to":"typst_utils::Static::hash","relation":"owns"},{"from":"typst_utils::Static::clone","to":"typst_utils::Static","relation":"uses"},{"from":"typst_utils::Static::deref","to":"core::ops::deref::Deref","relation":"uses"},{"from":"typst_utils::Static::deref","to":"typst_utils::Static","relation":"uses"},{"from":"typst_utils::Static::eq","to":"typst_utils::Static","relation":"uses"},{"from":"typst_utils::Static::fmt","to":"core::fmt::Error","relation":"uses"},{"from":"typst_utils::Static::fmt","to":"core::fmt::Formatter","relation":"uses"},{"from":"typst_utils::Static::fmt","to":"core::result::Result","relation":"uses"},{"from":"typst_utils::Static::fmt","to":"typst_utils::Static","relation":"uses"},{"from":"typst_utils::Static::hash","to":"typst_utils::Static","relation":"uses"},{"from":"typst_utils::bitset","to":"alloc::fmt","relation":"uses"},{"from":"typst_utils::bitset","to":"core::fmt::Debug","relation":"uses"},{"from":"typst_utils::bitset","to":"core::fmt::Formatter","relation":"uses"},{"from":"typst_utils::bitset","to":"core::fmt::macros::Debug","relation":"uses"},{"from":"typst_utils::bitset","to":"thin_vec::ThinVec","relation":"uses"},{"from":"typst_utils::bitset","to":"typst_utils::bitset::BitSet","relation":"owns"},{"from":"typst_utils::bitset","to":"typst_utils::bitset::SmallBitSet","relation":"owns"},{"from":"typst_utils::bitset::BitSet","to":"thin_vec::ThinVec","relation":"uses"},{"from":"typst_utils::bitset::BitSet","to":"typst_utils::bitset::BitSet::clone","relation":"owns"},{"from":"typst_utils::bitset::BitSet","to":"typst_utils::bitset::BitSet::contains","relation":"owns"},{"from":"typst_utils::bitset::BitSet","to":"typst_utils::bitset::BitSet::default","relation":"owns"},{"from":"typst_utils::bitset::BitSet","to":"typst_utils::bitset::BitSet::eq","relation":"owns"},{"from":"typst_utils::bitset::BitSet","to":"typst_utils::bitset::BitSet::fmt","relation":"owns"},{"from":"typst_utils::bitset::BitSet","to":"typst_utils::bitset::BitSet::hash","relation":"owns"},{"from":"typst_utils::bitset::BitSet","to":"typst_utils::bitset::BitSet::insert","relation":"owns"},{"from":"typst_utils::bitset::BitSet","to":"typst_utils::bitset::BitSet::new","relation":"owns"},{"from":"typst_utils::bitset::BitSet::clone","to":"typst_utils::bitset::BitSet","relation":"uses"},{"from":"typst_utils::bitset::BitSet::contains","to":"typst_utils::bitset::BitSet","relation":"uses"},{"from":"typst_utils::bitset::BitSet::default","to":"typst_utils::bitset::BitSet","relation":"uses"},{"from":"typst_utils::bitset::BitSet::eq","to":"typst_utils::bitset::BitSet","relation":"uses"},{"from":"typst_utils::bitset::BitSet::fmt","to":"core::fmt::Error","relation":"uses"},{"from":"typst_utils::bitset::BitSet::fmt","to":"core::fmt::Formatter","relation":"uses"},{"from":"typst_utils::bitset::BitSet::fmt","to":"core::result::Result","relation":"uses"},{"from":"typst_utils::bitset::BitSet::fmt","to":"typst_utils::bitset::BitSet","relation":"uses"},{"from":"typst_utils::bitset::BitSet::hash","to":"typst_utils::bitset::BitSet","relation":"uses"},{"from":"typst_utils::bitset::BitSet::insert","to":"typst_utils::bitset::BitSet","relation":"uses"},{"from":"typst_utils::bitset::BitSet::new","to":"typst_utils::bitset::BitSet","relation":"uses"},{"from":"typst_utils::bitset::SmallBitSet","to":"typst_utils::bitset::BitSet","relation":"uses"},{"from":"typst_utils::bitset::SmallBitSet","to":"typst_utils::bitset::SmallBitSet::clone","relation":"owns"},{"from":"typst_utils::bitset::SmallBitSet","to":"typst_utils::bitset::SmallBitSet::contains","relation":"owns"},{"from":"typst_utils::bitset::SmallBitSet","to":"typst_utils::bitset::SmallBitSet::default","relation":"owns"},{"from":"typst_utils::bitset::SmallBitSet","to":"typst_utils::bitset::SmallBitSet::eq","relation":"owns"},{"from":"typst_utils::bitset::SmallBitSet","to":"typst_utils::bitset::SmallBitSet::fmt","relation":"owns"},{"from":"typst_utils::bitset::SmallBitSet","to":"typst_utils::bitset::SmallBitSet::hash","relation":"owns"},{"from":"typst_utils::bitset::SmallBitSet","to":"typst_utils::bitset::SmallBitSet::insert","relation":"owns"},{"from":"typst_utils::bitset::SmallBitSet","to":"typst_utils::bitset::SmallBitSet::new","relation":"owns"},{"from":"typst_utils::bitset::SmallBitSet::clone","to":"typst_utils::bitset::SmallBitSet","relation":"uses"},{"from":"typst_utils::bitset::SmallBitSet::contains","to":"typst_utils::bitset::SmallBitSet","relation":"uses"},{"from":"typst_utils::bitset::SmallBitSet::default","to":"typst_utils::bitset::SmallBitSet","relation":"uses"},{"from":"typst_utils::bitset::SmallBitSet::eq","to":"typst_utils::bitset::SmallBitSet","relation":"uses"},{"from":"typst_utils::bitset::SmallBitSet::fmt","to":"core::fmt::Error","relation":"uses"},{"from":"typst_utils::bitset::SmallBitSet::fmt","to":"core::fmt::Formatter","relation":"uses"},{"from":"typst_utils::bitset::SmallBitSet::fmt","to":"core::result::Result","relation":"uses"},{"from":"typst_utils::bitset::SmallBitSet::fmt","to":"typst_utils::bitset::SmallBitSet","relation":"uses"},{"from":"typst_utils::bitset::SmallBitSet::hash","to":"typst_utils::bitset::SmallBitSet","relation":"uses"},{"from":"typst_utils::bitset::SmallBitSet::insert","to":"typst_utils::bitset::SmallBitSet","relation":"uses"},{"from":"typst_utils::bitset::SmallBitSet::new","to":"typst_utils::bitset::SmallBitSet","relation":"uses"},{"from":"typst_utils::debug","to":"core::fmt::Debug","relation":"uses"},{"from":"typst_utils::debug","to":"core::marker::Sized","relation":"uses"},{"from":"typst_utils::default_math_class","to":"core::option::Option","relation":"uses"},{"from":"typst_utils::default_math_class","to":"unicode_math_class::MathClass","relation":"uses"},{"from":"typst_utils::defer","to":"core::marker::Sized","relation":"uses"},{"from":"typst_utils::defer","to":"core::ops::deref::DerefMut","relation":"uses"},{"from":"typst_utils::deferred","to":"alloc::sync::Arc","relation":"uses"},{"from":"typst_utils::deferred","to":"once_cell::sync::OnceCell","relation":"uses"},{"from":"typst_utils::deferred","to":"typst_utils::deferred::Deferred","relation":"owns"},{"from":"typst_utils::deferred::Deferred","to":"alloc::alloc::Global","relation":"uses"},{"from":"typst_utils::deferred::Deferred","to":"alloc::sync::Arc","relation":"uses"},{"from":"typst_utils::deferred::Deferred","to":"once_cell::sync::OnceCell","relation":"uses"},{"from":"typst_utils::deferred::Deferred","to":"typst_utils::deferred::Deferred::clone","relation":"owns"},{"from":"typst_utils::deferred::Deferred","to":"typst_utils::deferred::Deferred::new","relation":"owns"},{"from":"typst_utils::deferred::Deferred","to":"typst_utils::deferred::Deferred::wait","relation":"owns"},{"from":"typst_utils::deferred::Deferred::clone","to":"typst_utils::deferred::Deferred","relation":"uses"},{"from":"typst_utils::deferred::Deferred::new","to":"typst_utils::deferred::Deferred","relation":"uses"},{"from":"typst_utils::deferred::Deferred::wait","to":"typst_utils::deferred::Deferred","relation":"uses"},{"from":"typst_utils::display","to":"core::fmt::Display","relation":"uses"},{"from":"typst_utils::display","to":"core::marker::Sized","relation":"uses"},{"from":"typst_utils::duration","to":"alloc::fmt","relation":"uses"},{"from":"typst_utils::duration","to":"core::fmt::Display","relation":"uses"},{"from":"typst_utils::duration","to":"core::fmt::Formatter","relation":"uses"},{"from":"typst_utils::duration","to":"core::fmt::Write","relation":"uses"},{"from":"typst_utils::duration","to":"core::time::Duration","relation":"uses"},{"from":"typst_utils::duration","to":"typst_utils::duration::DurationDisplay","relation":"owns"},{"from":"typst_utils::duration","to":"typst_utils::duration::format_duration","relation":"owns"},{"from":"typst_utils::duration","to":"typst_utils::round::round_with_precision","relation":"uses"},{"from":"typst_utils::duration::DurationDisplay","to":"core::time::Duration","relation":"uses"},{"from":"typst_utils::duration::DurationDisplay","to":"typst_utils::duration::DurationDisplay::fmt","relation":"owns"},{"from":"typst_utils::duration::DurationDisplay::fmt","to":"core::fmt::Error","relation":"uses"},{"from":"typst_utils::duration::DurationDisplay::fmt","to":"core::fmt::Formatter","relation":"uses"},{"from":"typst_utils::duration::DurationDisplay::fmt","to":"core::result::Result","relation":"uses"},{"from":"typst_utils::duration::DurationDisplay::fmt","to":"typst_utils::duration::DurationDisplay","relation":"uses"},{"from":"typst_utils::duration::format_duration","to":"core::fmt::Display","relation":"uses"},{"from":"typst_utils::duration::format_duration","to":"core::marker::Sized","relation":"uses"},{"from":"typst_utils::duration::format_duration","to":"core::time::Duration","relation":"uses"},{"from":"typst_utils::fat","to":"core::alloc::layout::Layout","relation":"uses"},{"from":"typst_utils::fat","to":"core::mem","relation":"uses"},{"from":"typst_utils::fat","to":"core::ptr::non_null::NonNull","relation":"uses"},{"from":"typst_utils::fat","to":"typst_utils::fat::FatPointer","relation":"owns"},{"from":"typst_utils::fat","to":"typst_utils::fat::from_raw_parts","relation":"owns"},{"from":"typst_utils::fat","to":"typst_utils::fat::from_raw_parts_mut","relation":"owns"},{"from":"typst_utils::fat","to":"typst_utils::fat::vtable","relation":"owns"},{"from":"typst_utils::fat::vtable","to":"core::ptr::non_null::NonNull","relation":"uses"},{"from":"typst_utils::hash","to":"alloc::fmt","relation":"uses"},{"from":"typst_utils::hash","to":"core::fmt::Debug","relation":"uses"},{"from":"typst_utils::hash","to":"core::fmt::macros::Debug","relation":"uses"},{"from":"typst_utils::hash","to":"core::hash::Hash","relation":"uses"},{"from":"typst_utils::hash","to":"core::hash::Hasher","relation":"uses"},{"from":"typst_utils::hash","to":"core::hash::macros::Hash","relation":"uses"},{"from":"typst_utils::hash","to":"core::ops::deref::Deref","relation":"uses"},{"from":"typst_utils::hash","to":"core::ops::deref::DerefMut","relation":"uses"},{"from":"typst_utils::hash","to":"core::sync::atomic::Ordering","relation":"uses"},{"from":"typst_utils::hash","to":"portable_atomic::AtomicU128","relation":"uses"},{"from":"typst_utils::hash","to":"siphasher::sip128::Hasher128","relation":"uses"},{"from":"typst_utils::hash","to":"siphasher::sip128::SipHasher13","relation":"uses"},{"from":"typst_utils::hash","to":"typst_utils::hash::HashLock","relation":"owns"},{"from":"typst_utils::hash","to":"typst_utils::hash::LazyHash","relation":"owns"},{"from":"typst_utils::hash","to":"typst_utils::hash::ManuallyHash","relation":"owns"},{"from":"typst_utils::hash","to":"typst_utils::hash::hash128","relation":"owns"},{"from":"typst_utils::hash::HashLock","to":"portable_atomic::AtomicU128","relation":"uses"},{"from":"typst_utils::hash::HashLock","to":"typst_utils::hash::HashLock::clone","relation":"owns"},{"from":"typst_utils::hash::HashLock","to":"typst_utils::hash::HashLock::default","relation":"owns"},{"from":"typst_utils::hash::HashLock","to":"typst_utils::hash::HashLock::get","relation":"owns"},{"from":"typst_utils::hash::HashLock","to":"typst_utils::hash::HashLock::get_or_insert_with","relation":"owns"},{"from":"typst_utils::hash::HashLock","to":"typst_utils::hash::HashLock::new","relation":"owns"},{"from":"typst_utils::hash::HashLock","to":"typst_utils::hash::HashLock::reset","relation":"owns"},{"from":"typst_utils::hash::HashLock::clone","to":"typst_utils::hash::HashLock","relation":"uses"},{"from":"typst_utils::hash::HashLock::default","to":"typst_utils::hash::HashLock","relation":"uses"},{"from":"typst_utils::hash::HashLock::get","to":"typst_utils::hash::HashLock","relation":"uses"},{"from":"typst_utils::hash::HashLock::get_or_insert_with","to":"core::marker::Sized","relation":"uses"},{"from":"typst_utils::hash::HashLock::get_or_insert_with","to":"core::ops::function::FnOnce","relation":"uses"},{"from":"typst_utils::hash::HashLock::get_or_insert_with","to":"typst_utils::hash::HashLock","relation":"uses"},{"from":"typst_utils::hash::HashLock::new","to":"typst_utils::hash::HashLock","relation":"uses"},{"from":"typst_utils::hash::HashLock::reset","to":"typst_utils::hash::HashLock","relation":"uses"},{"from":"typst_utils::hash::LazyHash","to":"typst_utils::hash::HashLock","relation":"uses"},{"from":"typst_utils::hash::LazyHash","to":"typst_utils::hash::LazyHash::Target","relation":"owns"},{"from":"typst_utils::hash::LazyHash","to":"typst_utils::hash::LazyHash::clone","relation":"owns"},{"from":"typst_utils::hash::LazyHash","to":"typst_utils::hash::LazyHash::default","relation":"owns"},{"from":"typst_utils::hash::LazyHash","to":"typst_utils::hash::LazyHash::deref","relation":"owns"},{"from":"typst_utils::hash::LazyHash","to":"typst_utils::hash::LazyHash::deref_mut","relation":"owns"},{"from":"typst_utils::hash::LazyHash","to":"typst_utils::hash::LazyHash::eq","relation":"owns"},{"from":"typst_utils::hash::LazyHash","to":"typst_utils::hash::LazyHash::fmt","relation":"owns"},{"from":"typst_utils::hash::LazyHash","to":"typst_utils::hash::LazyHash::from","relation":"owns"},{"from":"typst_utils::hash::LazyHash","to":"typst_utils::hash::LazyHash::hash","relation":"owns"},{"from":"typst_utils::hash::LazyHash","to":"typst_utils::hash::LazyHash::into_inner","relation":"owns"},{"from":"typst_utils::hash::LazyHash","to":"typst_utils::hash::LazyHash::load_or_compute_hash","relation":"owns"},{"from":"typst_utils::hash::LazyHash","to":"typst_utils::hash::LazyHash::new","relation":"owns"},{"from":"typst_utils::hash::LazyHash::clone","to":"typst_utils::hash::LazyHash","relation":"uses"},{"from":"typst_utils::hash::LazyHash::default","to":"typst_utils::hash::LazyHash","relation":"uses"},{"from":"typst_utils::hash::LazyHash::deref","to":"core::ops::deref::Deref","relation":"uses"},{"from":"typst_utils::hash::LazyHash::deref","to":"typst_utils::hash::LazyHash","relation":"uses"},{"from":"typst_utils::hash::LazyHash::deref_mut","to":"core::ops::deref::Deref","relation":"uses"},{"from":"typst_utils::hash::LazyHash::deref_mut","to":"typst_utils::hash::LazyHash","relation":"uses"},{"from":"typst_utils::hash::LazyHash::eq","to":"typst_utils::hash::LazyHash","relation":"uses"},{"from":"typst_utils::hash::LazyHash::fmt","to":"core::fmt::Error","relation":"uses"},{"from":"typst_utils::hash::LazyHash::fmt","to":"core::fmt::Formatter","relation":"uses"},{"from":"typst_utils::hash::LazyHash::fmt","to":"core::result::Result","relation":"uses"},{"from":"typst_utils::hash::LazyHash::fmt","to":"typst_utils::hash::LazyHash","relation":"uses"},{"from":"typst_utils::hash::LazyHash::from","to":"typst_utils::hash::LazyHash","relation":"uses"},{"from":"typst_utils::hash::LazyHash::hash","to":"typst_utils::hash::LazyHash","relation":"uses"},{"from":"typst_utils::hash::LazyHash::into_inner","to":"typst_utils::hash::LazyHash","relation":"uses"},{"from":"typst_utils::hash::LazyHash::load_or_compute_hash","to":"typst_utils::hash::LazyHash","relation":"uses"},{"from":"typst_utils::hash::LazyHash::new","to":"typst_utils::hash::LazyHash","relation":"uses"},{"from":"typst_utils::hash::ManuallyHash","to":"typst_utils::hash::ManuallyHash::Target","relation":"owns"},{"from":"typst_utils::hash::ManuallyHash","to":"typst_utils::hash::ManuallyHash::clone","relation":"owns"},{"from":"typst_utils::hash::ManuallyHash","to":"typst_utils::hash::ManuallyHash::deref","relation":"owns"},{"from":"typst_utils::hash::ManuallyHash","to":"typst_utils::hash::ManuallyHash::eq","relation":"owns"},{"from":"typst_utils::hash::ManuallyHash","to":"typst_utils::hash::ManuallyHash::fmt","relation":"owns"},{"from":"typst_utils::hash::ManuallyHash","to":"typst_utils::hash::ManuallyHash::hash","relation":"owns"},{"from":"typst_utils::hash::ManuallyHash","to":"typst_utils::hash::ManuallyHash::into_inner","relation":"owns"},{"from":"typst_utils::hash::ManuallyHash","to":"typst_utils::hash::ManuallyHash::new","relation":"owns"},{"from":"typst_utils::hash::ManuallyHash::clone","to":"typst_utils::hash::ManuallyHash","relation":"uses"},{"from":"typst_utils::hash::ManuallyHash::deref","to":"core::ops::deref::Deref","relation":"uses"},{"from":"typst_utils::hash::ManuallyHash::deref","to":"typst_utils::hash::ManuallyHash","relation":"uses"},{"from":"typst_utils::hash::ManuallyHash::eq","to":"typst_utils::hash::ManuallyHash","relation":"uses"},{"from":"typst_utils::hash::ManuallyHash::fmt","to":"core::fmt::Error","relation":"uses"},{"from":"typst_utils::hash::ManuallyHash::fmt","to":"core::fmt::Formatter","relation":"uses"},{"from":"typst_utils::hash::ManuallyHash::fmt","to":"core::result::Result","relation":"uses"},{"from":"typst_utils::hash::ManuallyHash::fmt","to":"typst_utils::hash::ManuallyHash","relation":"uses"},{"from":"typst_utils::hash::ManuallyHash::hash","to":"typst_utils::hash::ManuallyHash","relation":"uses"},{"from":"typst_utils::hash::ManuallyHash::into_inner","to":"typst_utils::hash::ManuallyHash","relation":"uses"},{"from":"typst_utils::hash::ManuallyHash::new","to":"typst_utils::hash::ManuallyHash","relation":"uses"},{"from":"typst_utils::listset","to":"core::ops::deref::DerefMut","relation":"uses"},{"from":"typst_utils::listset","to":"typst_utils::listset::ListSet","relation":"owns"},{"from":"typst_utils::listset::ListSet","to":"typst_utils::listset::ListSet::contains","relation":"owns"},{"from":"typst_utils::listset::ListSet","to":"typst_utils::listset::ListSet::is_empty","relation":"owns"},{"from":"typst_utils::listset::ListSet","to":"typst_utils::listset::ListSet::new","relation":"owns"},{"from":"typst_utils::listset::ListSet::contains","to":"typst_utils::listset::ListSet","relation":"uses"},{"from":"typst_utils::listset::ListSet::is_empty","to":"typst_utils::listset::ListSet","relation":"uses"},{"from":"typst_utils::listset::ListSet::new","to":"typst_utils::listset::ListSet","relation":"uses"},{"from":"typst_utils::option::Option::map_or_default","to":"core::option::Option","relation":"uses"},{"from":"typst_utils::option_eq","to":"core::option::Option","relation":"uses"},{"from":"typst_utils::pico","to":"alloc::fmt","relation":"uses"},{"from":"typst_utils::pico","to":"core::borrow::Borrow","relation":"uses"},{"from":"typst_utils::pico","to":"core::cmp::Ordering","relation":"uses"},{"from":"typst_utils::pico","to":"core::fmt::Debug","relation":"uses"},{"from":"typst_utils::pico","to":"core::fmt::Display","relation":"uses"},{"from":"typst_utils::pico","to":"core::fmt::Formatter","relation":"uses"},{"from":"typst_utils::pico","to":"core::fmt::macros::Debug","relation":"uses"},{"from":"typst_utils::pico","to":"core::hash::Hash","relation":"uses"},{"from":"typst_utils::pico","to":"core::hash::Hasher","relation":"uses"},{"from":"typst_utils::pico","to":"core::hash::macros::Hash","relation":"uses"},{"from":"typst_utils::pico","to":"core::num::nonzero::NonZeroU64","relation":"uses"},{"from":"typst_utils::pico","to":"core::ops::deref::Deref","relation":"uses"},{"from":"typst_utils::pico","to":"rustc_hash::FxHashMap","relation":"uses"},{"from":"typst_utils::pico","to":"std::sync::lazy_lock::LazyLock","relation":"uses"},{"from":"typst_utils::pico","to":"std::sync::poison::rwlock::RwLock","relation":"uses"},{"from":"typst_utils::pico","to":"typst_utils::pico::Interner","relation":"owns"},{"from":"typst_utils::pico","to":"typst_utils::pico::PicoStr","relation":"owns"},{"from":"typst_utils::pico","to":"typst_utils::pico::ResolvedPicoStr","relation":"owns"},{"from":"typst_utils::pico","to":"typst_utils::pico::ResolvedPicoStrInner","relation":"owns"},{"from":"typst_utils::pico","to":"typst_utils::pico::bitcode","relation":"owns"},{"from":"typst_utils::pico","to":"typst_utils::pico::exceptions","relation":"owns"},{"from":"typst_utils::pico","to":"typst_utils::pico::failed_to_compile_time_intern","relation":"owns"},{"from":"typst_utils::pico::Interner","to":"alloc::alloc::Global","relation":"uses"},{"from":"typst_utils::pico::Interner","to":"alloc::vec::Vec","relation":"uses"},{"from":"typst_utils::pico::Interner","to":"rustc_hash::FxBuildHasher","relation":"uses"},{"from":"typst_utils::pico::Interner","to":"std::collections::hash::map::HashMap","relation":"uses"},{"from":"typst_utils::pico::Interner","to":"typst_utils::pico::PicoStr","relation":"uses"},{"from":"typst_utils::pico::PicoStr","to":"core::num::nonzero::NonZero","relation":"uses"},{"from":"typst_utils::pico::PicoStr","to":"typst_utils::pico::PicoStr::clone","relation":"owns"},{"from":"typst_utils::pico::PicoStr","to":"typst_utils::pico::PicoStr::constant","relation":"owns"},{"from":"typst_utils::pico::PicoStr","to":"typst_utils::pico::PicoStr::eq","relation":"owns"},{"from":"typst_utils::pico::PicoStr","to":"typst_utils::pico::PicoStr::fmt","relation":"owns"},{"from":"typst_utils::pico::PicoStr","to":"typst_utils::pico::PicoStr::get","relation":"owns"},{"from":"typst_utils::pico::PicoStr","to":"typst_utils::pico::PicoStr::hash","relation":"owns"},{"from":"typst_utils::pico::PicoStr","to":"typst_utils::pico::PicoStr::intern","relation":"owns"},{"from":"typst_utils::pico::PicoStr","to":"typst_utils::pico::PicoStr::resolve","relation":"owns"},{"from":"typst_utils::pico::PicoStr","to":"typst_utils::pico::PicoStr::try_constant","relation":"owns"},{"from":"typst_utils::pico::PicoStr::clone","to":"typst_utils::pico::PicoStr","relation":"uses"},{"from":"typst_utils::pico::PicoStr::constant","to":"typst_utils::pico::PicoStr","relation":"uses"},{"from":"typst_utils::pico::PicoStr::eq","to":"typst_utils::pico::PicoStr","relation":"uses"},{"from":"typst_utils::pico::PicoStr::fmt","to":"core::fmt::Error","relation":"uses"},{"from":"typst_utils::pico::PicoStr::fmt","to":"core::fmt::Formatter","relation":"uses"},{"from":"typst_utils::pico::PicoStr::fmt","to":"core::result::Result","relation":"uses"},{"from":"typst_utils::pico::PicoStr::fmt","to":"typst_utils::pico::PicoStr","relation":"uses"},{"from":"typst_utils::pico::PicoStr::get","to":"core::option::Option","relation":"uses"},{"from":"typst_utils::pico::PicoStr::get","to":"typst_utils::pico::PicoStr","relation":"uses"},{"from":"typst_utils::pico::PicoStr::hash","to":"typst_utils::pico::PicoStr","relation":"uses"},{"from":"typst_utils::pico::PicoStr::intern","to":"typst_utils::pico::PicoStr","relation":"uses"},{"from":"typst_utils::pico::PicoStr::resolve","to":"typst_utils::pico::PicoStr","relation":"uses"},{"from":"typst_utils::pico::PicoStr::resolve","to":"typst_utils::pico::ResolvedPicoStr","relation":"uses"},{"from":"typst_utils::pico::PicoStr::try_constant","to":"core::result::Result","relation":"uses"},{"from":"typst_utils::pico::PicoStr::try_constant","to":"typst_utils::pico::PicoStr","relation":"uses"},{"from":"typst_utils::pico::PicoStr::try_constant","to":"typst_utils::pico::bitcode::EncodingError","relation":"uses"},{"from":"typst_utils::pico::ResolvedPicoStr","to":"typst_utils::pico::ResolvedPicoStr::Target","relation":"owns"},{"from":"typst_utils::pico::ResolvedPicoStr","to":"typst_utils::pico::ResolvedPicoStr::as_ref","relation":"owns"},{"from":"typst_utils::pico::ResolvedPicoStr","to":"typst_utils::pico::ResolvedPicoStr::as_str","relation":"owns"},{"from":"typst_utils::pico::ResolvedPicoStr","to":"typst_utils::pico::ResolvedPicoStr::borrow","relation":"owns"},{"from":"typst_utils::pico::ResolvedPicoStr","to":"typst_utils::pico::ResolvedPicoStr::clone","relation":"owns"},{"from":"typst_utils::pico::ResolvedPicoStr","to":"typst_utils::pico::ResolvedPicoStr::cmp","relation":"owns"},{"from":"typst_utils::pico::ResolvedPicoStr","to":"typst_utils::pico::ResolvedPicoStr::deref","relation":"owns"},{"from":"typst_utils::pico::ResolvedPicoStr","to":"typst_utils::pico::ResolvedPicoStr::eq","relation":"owns"},{"from":"typst_utils::pico::ResolvedPicoStr","to":"typst_utils::pico::ResolvedPicoStr::fmt","relation":"owns"},{"from":"typst_utils::pico::ResolvedPicoStr","to":"typst_utils::pico::ResolvedPicoStr::fmt","relation":"owns"},{"from":"typst_utils::pico::ResolvedPicoStr","to":"typst_utils::pico::ResolvedPicoStr::hash","relation":"owns"},{"from":"typst_utils::pico::ResolvedPicoStr","to":"typst_utils::pico::ResolvedPicoStr::partial_cmp","relation":"owns"},{"from":"typst_utils::pico::ResolvedPicoStr","to":"typst_utils::pico::ResolvedPicoStrInner","relation":"uses"},{"from":"typst_utils::pico::ResolvedPicoStr::as_ref","to":"typst_utils::pico::ResolvedPicoStr","relation":"uses"},{"from":"typst_utils::pico::ResolvedPicoStr::as_str","to":"typst_utils::pico::ResolvedPicoStr","relation":"uses"},{"from":"typst_utils::pico::ResolvedPicoStr::borrow","to":"typst_utils::pico::ResolvedPicoStr","relation":"uses"},{"from":"typst_utils::pico::ResolvedPicoStr::clone","to":"typst_utils::pico::ResolvedPicoStr","relation":"uses"},{"from":"typst_utils::pico::ResolvedPicoStr::cmp","to":"core::cmp::Ordering","relation":"uses"},{"from":"typst_utils::pico::ResolvedPicoStr::cmp","to":"typst_utils::pico::ResolvedPicoStr","relation":"uses"},{"from":"typst_utils::pico::ResolvedPicoStr::deref","to":"core::ops::deref::Deref","relation":"uses"},{"from":"typst_utils::pico::ResolvedPicoStr::deref","to":"typst_utils::pico::ResolvedPicoStr","relation":"uses"},{"from":"typst_utils::pico::ResolvedPicoStr::eq","to":"typst_utils::pico::ResolvedPicoStr","relation":"uses"},{"from":"typst_utils::pico::ResolvedPicoStr::fmt","to":"core::fmt::Error","relation":"uses"},{"from":"typst_utils::pico::ResolvedPicoStr::fmt","to":"core::fmt::Error","relation":"uses"},{"from":"typst_utils::pico::ResolvedPicoStr::fmt","to":"core::fmt::Formatter","relation":"uses"},{"from":"typst_utils::pico::ResolvedPicoStr::fmt","to":"core::fmt::Formatter","relation":"uses"},{"from":"typst_utils::pico::ResolvedPicoStr::fmt","to":"core::result::Result","relation":"uses"},{"from":"typst_utils::pico::ResolvedPicoStr::fmt","to":"core::result::Result","relation":"uses"},{"from":"typst_utils::pico::ResolvedPicoStr::fmt","to":"typst_utils::pico::ResolvedPicoStr","relation":"uses"},{"from":"typst_utils::pico::ResolvedPicoStr::fmt","to":"typst_utils::pico::ResolvedPicoStr","relation":"uses"},{"from":"typst_utils::pico::ResolvedPicoStr::hash","to":"typst_utils::pico::ResolvedPicoStr","relation":"uses"},{"from":"typst_utils::pico::ResolvedPicoStr::partial_cmp","to":"core::cmp::Ordering","relation":"uses"},{"from":"typst_utils::pico::ResolvedPicoStr::partial_cmp","to":"core::option::Option","relation":"uses"},{"from":"typst_utils::pico::ResolvedPicoStr::partial_cmp","to":"typst_utils::pico::ResolvedPicoStr","relation":"uses"},{"from":"typst_utils::pico::ResolvedPicoStrInner","to":"typst_utils::pico::ResolvedPicoStrInner::clone","relation":"owns"},{"from":"typst_utils::pico::ResolvedPicoStrInner::clone","to":"typst_utils::pico::ResolvedPicoStrInner","relation":"uses"},{"from":"typst_utils::pico::bitcode","to":"typst_utils::pico::ResolvedPicoStr","relation":"uses"},{"from":"typst_utils::pico::bitcode","to":"typst_utils::pico::ResolvedPicoStrInner","relation":"uses"},{"from":"typst_utils::pico::bitcode","to":"typst_utils::pico::bitcode::EncodingError","relation":"owns"},{"from":"typst_utils::pico::bitcode","to":"typst_utils::pico::bitcode::decode","relation":"owns"},{"from":"typst_utils::pico::bitcode","to":"typst_utils::pico::bitcode::encode","relation":"owns"},{"from":"typst_utils::pico::bitcode::EncodingError","to":"typst_utils::pico::bitcode::EncodingError::message","relation":"owns"},{"from":"typst_utils::pico::bitcode::EncodingError::message","to":"typst_utils::pico::bitcode::EncodingError","relation":"uses"},{"from":"typst_utils::pico::bitcode::decode","to":"typst_utils::pico::ResolvedPicoStr","relation":"uses"},{"from":"typst_utils::pico::bitcode::encode","to":"core::result::Result","relation":"uses"},{"from":"typst_utils::pico::bitcode::encode","to":"typst_utils::pico::bitcode::EncodingError","relation":"uses"},{"from":"typst_utils::pico::exceptions","to":"core::cmp::Ordering","relation":"uses"},{"from":"typst_utils::pico::exceptions","to":"typst_utils::pico::exceptions::get","relation":"owns"},{"from":"typst_utils::pico::exceptions","to":"typst_utils::pico::exceptions::min","relation":"owns"},{"from":"typst_utils::pico::exceptions","to":"typst_utils::pico::exceptions::strcmp","relation":"owns"},{"from":"typst_utils::pico::exceptions::get","to":"core::option::Option","relation":"uses"},{"from":"typst_utils::pico::exceptions::strcmp","to":"core::cmp::Ordering","relation":"uses"},{"from":"typst_utils::pico::failed_to_compile_time_intern","to":"typst_utils::pico::bitcode::EncodingError","relation":"uses"},{"from":"typst_utils::protected","to":"typst_utils::protected::Protected","relation":"owns"},{"from":"typst_utils::protected::Protected","to":"typst_utils::protected::Protected::access","relation":"owns"},{"from":"typst_utils::protected::Protected","to":"typst_utils::protected::Protected::clone","relation":"owns"},{"from":"typst_utils::protected::Protected","to":"typst_utils::protected::Protected::fmt","relation":"owns"},{"from":"typst_utils::protected::Protected","to":"typst_utils::protected::Protected::from_raw","relation":"owns"},{"from":"typst_utils::protected::Protected","to":"typst_utils::protected::Protected::into_raw","relation":"owns"},{"from":"typst_utils::protected::Protected","to":"typst_utils::protected::Protected::new","relation":"owns"},{"from":"typst_utils::protected::Protected::access","to":"typst_utils::protected::Protected","relation":"uses"},{"from":"typst_utils::protected::Protected::clone","to":"typst_utils::protected::Protected","relation":"uses"},{"from":"typst_utils::protected::Protected::fmt","to":"core::fmt::Error","relation":"uses"},{"from":"typst_utils::protected::Protected::fmt","to":"core::fmt::Formatter","relation":"uses"},{"from":"typst_utils::protected::Protected::fmt","to":"core::result::Result","relation":"uses"},{"from":"typst_utils::protected::Protected::fmt","to":"typst_utils::protected::Protected","relation":"uses"},{"from":"typst_utils::protected::Protected::from_raw","to":"typst_utils::protected::Protected","relation":"uses"},{"from":"typst_utils::protected::Protected::into_raw","to":"typst_utils::protected::Protected","relation":"uses"},{"from":"typst_utils::protected::Protected::new","to":"typst_utils::protected::Protected","relation":"uses"},{"from":"typst_utils::round","to":"typst_utils::round::round_int_with_precision","relation":"owns"},{"from":"typst_utils::round","to":"typst_utils::round::round_with_precision","relation":"owns"},{"from":"typst_utils::round::round_int_with_precision","to":"core::option::Option","relation":"uses"},{"from":"typst_utils::scalar","to":"alloc::fmt","relation":"uses"},{"from":"typst_utils::scalar","to":"core::cmp::Ordering","relation":"uses"},{"from":"typst_utils::scalar","to":"core::fmt::Debug","relation":"uses"},{"from":"typst_utils::scalar","to":"core::fmt::Formatter","relation":"uses"},{"from":"typst_utils::scalar","to":"core::fmt::macros::Debug","relation":"uses"},{"from":"typst_utils::scalar","to":"core::hash::Hash","relation":"uses"},{"from":"typst_utils::scalar","to":"core::hash::Hasher","relation":"uses"},{"from":"typst_utils::scalar","to":"core::hash::macros::Hash","relation":"uses"},{"from":"typst_utils::scalar","to":"core::iter::traits::accum::Sum","relation":"uses"},{"from":"typst_utils::scalar","to":"core::ops::arith::Add","relation":"uses"},{"from":"typst_utils::scalar","to":"core::ops::arith::Div","relation":"uses"},{"from":"typst_utils::scalar","to":"core::ops::arith::Mul","relation":"uses"},{"from":"typst_utils::scalar","to":"core::ops::arith::Neg","relation":"uses"},{"from":"typst_utils::scalar","to":"core::ops::arith::Rem","relation":"uses"},{"from":"typst_utils::scalar","to":"core::ops::arith::Sub","relation":"uses"},{"from":"typst_utils::scalar","to":"typst_utils::Numeric","relation":"uses"},{"from":"typst_utils::scalar","to":"typst_utils::scalar::Scalar","relation":"owns"},{"from":"typst_utils::scalar::Scalar","to":"typst_utils::scalar::Scalar::Output","relation":"owns"},{"from":"typst_utils::scalar::Scalar","to":"typst_utils::scalar::Scalar::Output","relation":"owns"},{"from":"typst_utils::scalar::Scalar","to":"typst_utils::scalar::Scalar::Output","relation":"owns"},{"from":"typst_utils::scalar::Scalar","to":"typst_utils::scalar::Scalar::Output","relation":"owns"},{"from":"typst_utils::scalar::Scalar","to":"typst_utils::scalar::Scalar::Output","relation":"owns"},{"from":"typst_utils::scalar::Scalar","to":"typst_utils::scalar::Scalar::Output","relation":"owns"},{"from":"typst_utils::scalar::Scalar","to":"typst_utils::scalar::Scalar::Output","relation":"owns"},{"from":"typst_utils::scalar::Scalar","to":"typst_utils::scalar::Scalar::Output","relation":"owns"},{"from":"typst_utils::scalar::Scalar","to":"typst_utils::scalar::Scalar::Output","relation":"owns"},{"from":"typst_utils::scalar::Scalar","to":"typst_utils::scalar::Scalar::Output","relation":"owns"},{"from":"typst_utils::scalar::Scalar","to":"typst_utils::scalar::Scalar::Output","relation":"owns"},{"from":"typst_utils::scalar::Scalar","to":"typst_utils::scalar::Scalar::add","relation":"owns"},{"from":"typst_utils::scalar::Scalar","to":"typst_utils::scalar::Scalar::add","relation":"owns"},{"from":"typst_utils::scalar::Scalar","to":"typst_utils::scalar::Scalar::add_assign","relation":"owns"},{"from":"typst_utils::scalar::Scalar","to":"typst_utils::scalar::Scalar::add_assign","relation":"owns"},{"from":"typst_utils::scalar::Scalar","to":"typst_utils::scalar::Scalar::clone","relation":"owns"},{"from":"typst_utils::scalar::Scalar","to":"typst_utils::scalar::Scalar::cmp","relation":"owns"},{"from":"typst_utils::scalar::Scalar","to":"typst_utils::scalar::Scalar::default","relation":"owns"},{"from":"typst_utils::scalar::Scalar","to":"typst_utils::scalar::Scalar::div","relation":"owns"},{"from":"typst_utils::scalar::Scalar","to":"typst_utils::scalar::Scalar::div","relation":"owns"},{"from":"typst_utils::scalar::Scalar","to":"typst_utils::scalar::Scalar::div_assign","relation":"owns"},{"from":"typst_utils::scalar::Scalar","to":"typst_utils::scalar::Scalar::div_assign","relation":"owns"},{"from":"typst_utils::scalar::Scalar","to":"typst_utils::scalar::Scalar::eq","relation":"owns"},{"from":"typst_utils::scalar::Scalar","to":"typst_utils::scalar::Scalar::eq","relation":"owns"},{"from":"typst_utils::scalar::Scalar","to":"typst_utils::scalar::Scalar::fmt","relation":"owns"},{"from":"typst_utils::scalar::Scalar","to":"typst_utils::scalar::Scalar::from","relation":"owns"},{"from":"typst_utils::scalar::Scalar","to":"typst_utils::scalar::Scalar::get","relation":"owns"},{"from":"typst_utils::scalar::Scalar","to":"typst_utils::scalar::Scalar::hash","relation":"owns"},{"from":"typst_utils::scalar::Scalar","to":"typst_utils::scalar::Scalar::is_finite","relation":"owns"},{"from":"typst_utils::scalar::Scalar","to":"typst_utils::scalar::Scalar::mul","relation":"owns"},{"from":"typst_utils::scalar::Scalar","to":"typst_utils::scalar::Scalar::mul","relation":"owns"},{"from":"typst_utils::scalar::Scalar","to":"typst_utils::scalar::Scalar::mul_assign","relation":"owns"},{"from":"typst_utils::scalar::Scalar","to":"typst_utils::scalar::Scalar::mul_assign","relation":"owns"},{"from":"typst_utils::scalar::Scalar","to":"typst_utils::scalar::Scalar::neg","relation":"owns"},{"from":"typst_utils::scalar::Scalar","to":"typst_utils::scalar::Scalar::new","relation":"owns"},{"from":"typst_utils::scalar::Scalar","to":"typst_utils::scalar::Scalar::partial_cmp","relation":"owns"},{"from":"typst_utils::scalar::Scalar","to":"typst_utils::scalar::Scalar::powi","relation":"owns"},{"from":"typst_utils::scalar::Scalar","to":"typst_utils::scalar::Scalar::rem","relation":"owns"},{"from":"typst_utils::scalar::Scalar","to":"typst_utils::scalar::Scalar::rem","relation":"owns"},{"from":"typst_utils::scalar::Scalar","to":"typst_utils::scalar::Scalar::rem_assign","relation":"owns"},{"from":"typst_utils::scalar::Scalar","to":"typst_utils::scalar::Scalar::rem_assign","relation":"owns"},{"from":"typst_utils::scalar::Scalar","to":"typst_utils::scalar::Scalar::sqrt","relation":"owns"},{"from":"typst_utils::scalar::Scalar","to":"typst_utils::scalar::Scalar::sub","relation":"owns"},{"from":"typst_utils::scalar::Scalar","to":"typst_utils::scalar::Scalar::sub","relation":"owns"},{"from":"typst_utils::scalar::Scalar","to":"typst_utils::scalar::Scalar::sub_assign","relation":"owns"},{"from":"typst_utils::scalar::Scalar","to":"typst_utils::scalar::Scalar::sub_assign","relation":"owns"},{"from":"typst_utils::scalar::Scalar","to":"typst_utils::scalar::Scalar::sum","relation":"owns"},{"from":"typst_utils::scalar::Scalar","to":"typst_utils::scalar::Scalar::sum","relation":"owns"},{"from":"typst_utils::scalar::Scalar","to":"typst_utils::scalar::Scalar::zero","relation":"owns"},{"from":"typst_utils::scalar::Scalar::Output","to":"typst_utils::scalar::Scalar","relation":"uses"},{"from":"typst_utils::scalar::Scalar::Output","to":"typst_utils::scalar::Scalar","relation":"uses"},{"from":"typst_utils::scalar::Scalar::Output","to":"typst_utils::scalar::Scalar","relation":"uses"},{"from":"typst_utils::scalar::Scalar::Output","to":"typst_utils::scalar::Scalar","relation":"uses"},{"from":"typst_utils::scalar::Scalar::Output","to":"typst_utils::scalar::Scalar","relation":"uses"},{"from":"typst_utils::scalar::Scalar::Output","to":"typst_utils::scalar::Scalar","relation":"uses"},{"from":"typst_utils::scalar::Scalar::Output","to":"typst_utils::scalar::Scalar","relation":"uses"},{"from":"typst_utils::scalar::Scalar::Output","to":"typst_utils::scalar::Scalar","relation":"uses"},{"from":"typst_utils::scalar::Scalar::Output","to":"typst_utils::scalar::Scalar","relation":"uses"},{"from":"typst_utils::scalar::Scalar::Output","to":"typst_utils::scalar::Scalar","relation":"uses"},{"from":"typst_utils::scalar::Scalar::Output","to":"typst_utils::scalar::Scalar","relation":"uses"},{"from":"typst_utils::scalar::Scalar::add","to":"core::ops::arith::Add","relation":"uses"},{"from":"typst_utils::scalar::Scalar::add","to":"core::ops::arith::Add","relation":"uses"},{"from":"typst_utils::scalar::Scalar::add","to":"typst_utils::scalar::Scalar","relation":"uses"},{"from":"typst_utils::scalar::Scalar::add","to":"typst_utils::scalar::Scalar","relation":"uses"},{"from":"typst_utils::scalar::Scalar::add_assign","to":"typst_utils::scalar::Scalar","relation":"uses"},{"from":"typst_utils::scalar::Scalar::add_assign","to":"typst_utils::scalar::Scalar","relation":"uses"},{"from":"typst_utils::scalar::Scalar::clone","to":"typst_utils::scalar::Scalar","relation":"uses"},{"from":"typst_utils::scalar::Scalar::cmp","to":"core::cmp::Ordering","relation":"uses"},{"from":"typst_utils::scalar::Scalar::cmp","to":"typst_utils::scalar::Scalar","relation":"uses"},{"from":"typst_utils::scalar::Scalar::default","to":"typst_utils::scalar::Scalar","relation":"uses"},{"from":"typst_utils::scalar::Scalar::div","to":"core::ops::arith::Div","relation":"uses"},{"from":"typst_utils::scalar::Scalar::div","to":"core::ops::arith::Div","relation":"uses"},{"from":"typst_utils::scalar::Scalar::div","to":"typst_utils::scalar::Scalar","relation":"uses"},{"from":"typst_utils::scalar::Scalar::div","to":"typst_utils::scalar::Scalar","relation":"uses"},{"from":"typst_utils::scalar::Scalar::div_assign","to":"typst_utils::scalar::Scalar","relation":"uses"},{"from":"typst_utils::scalar::Scalar::div_assign","to":"typst_utils::scalar::Scalar","relation":"uses"},{"from":"typst_utils::scalar::Scalar::eq","to":"typst_utils::scalar::Scalar","relation":"uses"},{"from":"typst_utils::scalar::Scalar::eq","to":"typst_utils::scalar::Scalar","relation":"uses"},{"from":"typst_utils::scalar::Scalar::fmt","to":"core::fmt::Error","relation":"uses"},{"from":"typst_utils::scalar::Scalar::fmt","to":"core::fmt::Formatter","relation":"uses"},{"from":"typst_utils::scalar::Scalar::fmt","to":"core::result::Result","relation":"uses"},{"from":"typst_utils::scalar::Scalar::fmt","to":"typst_utils::scalar::Scalar","relation":"uses"},{"from":"typst_utils::scalar::Scalar::from","to":"typst_utils::scalar::Scalar","relation":"uses"},{"from":"typst_utils::scalar::Scalar::get","to":"typst_utils::scalar::Scalar","relation":"uses"},{"from":"typst_utils::scalar::Scalar::hash","to":"typst_utils::scalar::Scalar","relation":"uses"},{"from":"typst_utils::scalar::Scalar::is_finite","to":"typst_utils::scalar::Scalar","relation":"uses"},{"from":"typst_utils::scalar::Scalar::mul","to":"core::ops::arith::Mul","relation":"uses"},{"from":"typst_utils::scalar::Scalar::mul","to":"core::ops::arith::Mul","relation":"uses"},{"from":"typst_utils::scalar::Scalar::mul","to":"typst_utils::scalar::Scalar","relation":"uses"},{"from":"typst_utils::scalar::Scalar::mul","to":"typst_utils::scalar::Scalar","relation":"uses"},{"from":"typst_utils::scalar::Scalar::mul_assign","to":"typst_utils::scalar::Scalar","relation":"uses"},{"from":"typst_utils::scalar::Scalar::mul_assign","to":"typst_utils::scalar::Scalar","relation":"uses"},{"from":"typst_utils::scalar::Scalar::neg","to":"core::ops::arith::Neg","relation":"uses"},{"from":"typst_utils::scalar::Scalar::neg","to":"typst_utils::scalar::Scalar","relation":"uses"},{"from":"typst_utils::scalar::Scalar::new","to":"typst_utils::scalar::Scalar","relation":"uses"},{"from":"typst_utils::scalar::Scalar::partial_cmp","to":"core::cmp::Ordering","relation":"uses"},{"from":"typst_utils::scalar::Scalar::partial_cmp","to":"core::option::Option","relation":"uses"},{"from":"typst_utils::scalar::Scalar::partial_cmp","to":"typst_utils::scalar::Scalar","relation":"uses"},{"from":"typst_utils::scalar::Scalar::powi","to":"typst_utils::scalar::Scalar","relation":"uses"},{"from":"typst_utils::scalar::Scalar::rem","to":"core::ops::arith::Rem","relation":"uses"},{"from":"typst_utils::scalar::Scalar::rem","to":"core::ops::arith::Rem","relation":"uses"},{"from":"typst_utils::scalar::Scalar::rem","to":"typst_utils::scalar::Scalar","relation":"uses"},{"from":"typst_utils::scalar::Scalar::rem","to":"typst_utils::scalar::Scalar","relation":"uses"},{"from":"typst_utils::scalar::Scalar::rem_assign","to":"typst_utils::scalar::Scalar","relation":"uses"},{"from":"typst_utils::scalar::Scalar::rem_assign","to":"typst_utils::scalar::Scalar","relation":"uses"},{"from":"typst_utils::scalar::Scalar::sqrt","to":"typst_utils::scalar::Scalar","relation":"uses"},{"from":"typst_utils::scalar::Scalar::sub","to":"core::ops::arith::Sub","relation":"uses"},{"from":"typst_utils::scalar::Scalar::sub","to":"core::ops::arith::Sub","relation":"uses"},{"from":"typst_utils::scalar::Scalar::sub","to":"typst_utils::scalar::Scalar","relation":"uses"},{"from":"typst_utils::scalar::Scalar::sub","to":"typst_utils::scalar::Scalar","relation":"uses"},{"from":"typst_utils::scalar::Scalar::sub_assign","to":"typst_utils::scalar::Scalar","relation":"uses"},{"from":"typst_utils::scalar::Scalar::sub_assign","to":"typst_utils::scalar::Scalar","relation":"uses"},{"from":"typst_utils::scalar::Scalar::sum","to":"typst_utils::scalar::Scalar","relation":"uses"},{"from":"typst_utils::scalar::Scalar::sum","to":"typst_utils::scalar::Scalar","relation":"uses"},{"from":"typst_utils::scalar::Scalar::zero","to":"typst_utils::scalar::Scalar","relation":"uses"},{"from":"typst_utils::sync::Arc::take","to":"alloc::alloc::Global","relation":"uses"},{"from":"typst_utils::sync::Arc::take","to":"alloc::sync::Arc","relation":"uses"},{"from":"typst_utils::version_","to":"typst_utils::version_::TypstVersion","relation":"owns"},{"from":"typst_utils::version_","to":"typst_utils::version_::display_commit","relation":"owns"},{"from":"typst_utils::version_","to":"typst_utils::version_::version","relation":"owns"},{"from":"typst_utils::version_::TypstVersion","to":"core::option::Option","relation":"uses"},{"from":"typst_utils::version_::TypstVersion","to":"typst_utils::version_::TypstVersion::clone","relation":"owns"},{"from":"typst_utils::version_::TypstVersion","to":"typst_utils::version_::TypstVersion::commit","relation":"owns"},{"from":"typst_utils::version_::TypstVersion","to":"typst_utils::version_::TypstVersion::fmt","relation":"owns"},{"from":"typst_utils::version_::TypstVersion","to":"typst_utils::version_::TypstVersion::major","relation":"owns"},{"from":"typst_utils::version_::TypstVersion","to":"typst_utils::version_::TypstVersion::minor","relation":"owns"},{"from":"typst_utils::version_::TypstVersion","to":"typst_utils::version_::TypstVersion::patch","relation":"owns"},{"from":"typst_utils::version_::TypstVersion","to":"typst_utils::version_::TypstVersion::raw","relation":"owns"},{"from":"typst_utils::version_::TypstVersion::clone","to":"typst_utils::version_::TypstVersion","relation":"uses"},{"from":"typst_utils::version_::TypstVersion::commit","to":"core::option::Option","relation":"uses"},{"from":"typst_utils::version_::TypstVersion::commit","to":"typst_utils::version_::TypstVersion","relation":"uses"},{"from":"typst_utils::version_::TypstVersion::fmt","to":"core::fmt::Error","relation":"uses"},{"from":"typst_utils::version_::TypstVersion::fmt","to":"core::fmt::Formatter","relation":"uses"},{"from":"typst_utils::version_::TypstVersion::fmt","to":"core::result::Result","relation":"uses"},{"from":"typst_utils::version_::TypstVersion::fmt","to":"typst_utils::version_::TypstVersion","relation":"uses"},{"from":"typst_utils::version_::TypstVersion::major","to":"typst_utils::version_::TypstVersion","relation":"uses"},{"from":"typst_utils::version_::TypstVersion::minor","to":"typst_utils::version_::TypstVersion","relation":"uses"},{"from":"typst_utils::version_::TypstVersion::patch","to":"typst_utils::version_::TypstVersion","relation":"uses"},{"from":"typst_utils::version_::TypstVersion::raw","to":"typst_utils::version_::TypstVersion","relation":"uses"},{"from":"typst_utils::version_::display_commit","to":"core::option::Option","relation":"uses"},{"from":"typst_utils::version_::version","to":"typst_utils::version_::TypstVersion","relation":"uses"}]}
